sphinx_visualized/__init__.py
sphinx_visualized/static/css/graph-panels.css
sphinx_visualized/static/html/includes-graph.html
sphinx_visualized/static/html/index.html
sphinx_visualized/static/html/link-graph.html
sphinx_visualized/static/html/toctree-graph.html
sphinx_visualized/static/js/convert-tree.js
sphinx_visualized/static/js/includes-graph.js
sphinx_visualized/static/js/link-graph.js
sphinx_visualized/static/js/tailwind-config.js
sphinx_visualized/static/js/toctree-graph.js
sphinx_visualized/static/svg/chevron-down.svg
sphinx_visualized/static/svg/document.svg
sphinx_visualized/static/svg/external.svg
sphinx_visualized/static/svg/home.svg
sphinx_visualized/static/svg/magnifying-glass-minus.svg
sphinx_visualized/static/svg/magnifying-glass-plus.svg
sphinx_visualized/static/svg/magnifying-glass.svg
sphinx_visualized/static/svg/map.svg
sphinx_visualized/static/svg/viewfinder.svg
sphinx_visualized-0.8.1.dist-info/LICENSE
sphinx_visualized-0.8.1.dist-info/METADATA
sphinx_visualized-0.8.1.dist-info/WHEEL
sphinx_visualized-0.8.1.dist-info/top_level.txt
sphinx_visualized-0.8.1.dist-info/RECORD
