Metadata-Version: 2.1
Name: sphinx-visualized
Version: 0.8.1
Summary: Visualization generator for Sphinx
Author-email: Jared Dillard <jared.dillard@gmail.com>
Maintainer-email: Jared Dillard <jared.dillard@gmail.com>
License: MIT
Project-URL: documentation, https://sphinx-visualized.readthedocs.io/en/latest/index.html
Project-URL: download, https://pypi.org/project/sphinx-visualized/
Project-URL: source, https://github.com/jdillard/sphinx-visualized
Project-URL: changelog, https://github.com/jdillard/sphinx-visualized/blob/master/CHANGELOG.rst
Classifier: License :: OSI Approved :: MIT License
Classifier: Topic :: Documentation :: Sphinx
Classifier: Programming Language :: Python :: 3.8
Classifier: Programming Language :: Python :: 3.9
Classifier: Programming Language :: Python :: 3.10
Classifier: Programming Language :: Python :: 3.11
Classifier: Framework :: Sphinx :: Extension
License-File: LICENSE
Requires-Dist: sphinx>=1.2
Provides-Extra: dev
Requires-Dist: tox; extra == "dev"
Requires-Dist: build; extra == "dev"
Requires-Dist: pre-commit; extra == "dev"
Requires-Dist: flake8; extra == "dev"
Requires-Dist: sphinx; extra == "dev"
Requires-Dist: pytest; extra == "dev"
